documentation/__init__.py
documentation/source/__init__.py
documentation/source/conf.py
logs/__init__.py
logs/client_log_config.py
logs/server_log_config.py
server/__init__.py
server/add_user.py
server/config_window.py
server/core.py
server/main_window.py
server/remove_user.py
server/start_window.py
server/dbase/__init__.py
server/dbase/database.py
unit_tests/__init__.py
unit_tests/test_client.py
unit_tests/test_server.py
utils/__init__.py
utils/config_messages.py
utils/decorators.py
utils/errors.py
utils/metaclasses.py
utils/server_socket_descriptor.py
utils/settings.py
net_mess_server-0.1.2.dist-info/METADATA
net_mess_server-0.1.2.dist-info/WHEEL
net_mess_server-0.1.2.dist-info/top_level.txt
net_mess_server-0.1.2.dist-info/RECORD
