Metadata-Version: 2.1
Name: net-mess-server
Version: 0.1.2
Summary: Network mess Server
Author: Maks-R
Author-email: ya@maks47.ru
Requires-Dist: PyQt5
Requires-Dist: sqlalchemy
Requires-Dist: pycryptodome
Requires-Dist: pycryptodomex
